RustQuant-0.0.17.dist-info/METADATA
RustQuant-0.0.17.dist-info/WHEEL
RustQuant-0.0.17.dist-info/license_files/LICENSE.md
RustQuant/__init__.py
RustQuant/RustQuant.abi3.so
RustQuant-0.0.17.dist-info/RECORD
