Metadata-Version: 2.1
Name: RustQuant
Version: 0.0.17
Classifier: Programming Language :: Rust
Classifier: Programming Language :: Python :: Implementation :: CPython
Classifier: Programming Language :: Python :: Implementation :: PyPy
License-File: LICENSE.md
Summary: A Rust library for quantitative finance tools.
Keywords: finance,quantitative,option-pricing,statistics,quantlib
License: GPL-3.0-or-later
Requires-Python: >=3.7
Project-URL: Source Code, https://github.com/avhz/RustQuant
